pointcloud_sax_reader/__init__.py
pointcloud_sax_reader/__main__.py
pointcloud_sax_reader/_core.pypy38-pp73-win_amd64.pyd
pointcloud_sax_reader-0.1.0.dist-info/METADATA
pointcloud_sax_reader-0.1.0.dist-info/WHEEL
pointcloud_sax_reader-0.1.0.dist-info/entry_points.txt
pointcloud_sax_reader-0.1.0.dist-info/licenses/LICENSE
pointcloud_sax_reader-0.1.0.dist-info/RECORD
